Metadata-Version: 2.1
Name: ktuvit-api-djangoy
Version: 0.0.1
Summary: Onofficial python client to ktuvit.me (screwzira) API 
Home-page: https://github.com/yious/ktuvit-api
Author: Django
License: UNKNOWN
Platform: UNKNOWN
Classifier: Programming Language :: Python :: 3
Classifier: Operating System :: OS Independent
Requires-Python: >=3.6
